 [ {"returncode":0,"message":"成功","result":{"seriesid":117,"paramtypeitems":[{"name":"基本参数","paramitems":[{"name":"车型名称","valueitems":[{"specid":15930,"value":"蒙迪欧 2013款 1.5L GTDi180舒适型"},{"specid":15504,"value":"蒙迪欧 2013款 1.5L GTDi180时尚型"},{"specid":15932,"value":"蒙迪欧 2013款 2.0L GTDi200时尚型"},{"specid":15933,"value":"蒙迪欧 2013款 2.0L GTDi200豪华型"},{"specid":15931,"value":"蒙迪欧 2013款 2.0L GTDi240豪华运动型"},{"specid":15854,"value":"蒙迪欧 2013款 2.0L GTDi240至尊型"},{"specid":16167,"value":"蒙迪欧 2013款 2.0L GTDi240旗舰型"}]},{"name":"厂商指导价(元)","valueitems":[{"specid":15930,"value":"17.98万"},{"specid":15504,"value":"18.98万"},{"specid":15932,"value":"20.28万"},{"specid":15933,"value":"22.28万"},{"specid":15931,"value":"24.28万"},{"specid":15854,"value":"25.28万"},{"specid":16167,"value":"26.58万"}]},{"name":"厂商","valueitems":[{"specid":15930,"value":"长安福特"},{"specid":15504,"value":"长安福特"},{"specid":15932,"value":"长安福特"},{"specid":15933,"value":"长安福特"},{"specid":15931,"value":"长安福特"},{"specid":15854,"value":"长安福特"},{"specid":16167,"value":"长安福特"}]},{"name":"级别","valueitems":[{"specid":15930,"value":"中型车"},{"specid":15504,"value":"中型车"},{"specid":15932,"value":"中型车"},{"specid":15933,"value":"中型车"},{"specid":15931,"value":"中型车"},{"specid":15854,"value":"中型车"},{"specid":16167,"value":"中型车"}]},{"name":"发动机","valueitems":[{"specid":15930,"value":"1.5T 181马力 L4"},{"specid":15504,"value":"1.5T 181马力 L4"},{"specid":15932,"value":"2.0T 203马力 L4"},{"specid":15933,"value":"2.0T 203马力 L4"},{"specid":15931,"value":"2.0T 242马力 L4"},{"specid":15854,"value":"2.0T 242马力 L4"},{"specid":16167,"value":"2.0T 242马力 L4"}]},{"name":"变速箱","valueitems":[{"specid":15930,"value":"6挡手自一体"},{"specid":15504,"value":"6挡手自一体"},{"specid":15932,"value":"6挡手自一体"},{"specid":15933,"value":"6挡手自一体"},{"specid":15931,"value":"6挡手自一体"},{"specid":15854,"value":"6挡手自一体"},{"specid":16167,"value":"6挡手自一体"}]},{"name":"长*宽*高(mm)","valueitems":[{"specid":15930,"value":"4860*1854*1480"},{"specid":15504,"value":"4860*1854*1480"},{"specid":15932,"value":"4860*1854*1480"},{"specid":15933,"value":"4860*1854*1480"},{"specid":15931,"value":"4860*1854*1480"},{"specid":15854,"value":"4860*1854*1480"},{"specid":16167,"value":"4860*1854*1480"}]},{"name":"车身结构","valueitems":[{"specid":15930,"value":"4门5座三厢车"},{"specid":15504,"value":"4门5座三厢车"},{"specid":15932,"value":"4门5座三厢车"},{"specid":15933,"value":"4门5座三厢车"},{"specid":15931,"value":"4门5座三厢车"},{"specid":15854,"value":"4门5座三厢车"},{"specid":16167,"value":"4门5座三厢车"}]},{"name":"最高车速(km/h)","valueitems":[{"specid":15930,"value":"200"},{"specid":15504,"value":"200"},{"specid":15932,"value":"208"},{"specid":15933,"value":"208"},{"specid":15931,"value":"218"},{"specid":15854,"value":"218"},{"specid":16167,"value":"218"}]},{"name":"官方0-100km/h加速(s)","valueitems":[{"specid":15930,"value":"9.3"},{"specid":15504,"value":"9.3"},{"specid":15932,"value":"8.1"},{"specid":15933,"value":"8.1"},{"specid":15931,"value":"7.6"},{"specid":15854,"value":"7.6"},{"specid":16167,"value":"7.6"}]},{"name":"实测0-100km/h加速(s)","valueitems":[{"specid":15930,"value":"-"},{"specid":15504,"value":"-"},{"specid":15932,"value":"-"},{"specid":15933,"value":"-"},{"specid":15931,"value":"-"},{"specid":15854,"value":"-"},{"specid":16167,"value":"8.13"}]},{"name":"实测100-0km/h制动(m)","valueitems":[{"specid":15930,"value":"-"},{"specid":15504,"value":"-"},{"specid":15932,"value":"-"},{"specid":15933,"value":"-"},{"specid":15931,"value":"-"},{"specid":15854,"value":"-"},{"specid":16167,"value":"41.72"}]},{"name":"实测油耗(L/100km)","valueitems":[{"specid":15930,"value":"-"},{"specid":15504,"value":"-"},{"specid":15932,"value":"-"},{"specid":15933,"value":"-"},{"specid":15931,"value":"-"},{"specid":15854,"value":"-"},{"specid":16167,"value":"-"}]},{"name":"工信部综合油耗(L/100km)","valueitems":[{"specid":15930,"value":"6.9"},{"specid":15504,"value":"6.9"},{"specid":15932,"value":"7.9"},{"specid":15933,"value":"7.9"},{"specid":15931,"value":"7.9"},{"specid":15854,"value":"7.9"},{"specid":16167,"value":"7.9"}]},{"name":"整车质保","valueitems":[{"specid":15930,"value":"三年或10万公里"},{"specid":15504,"value":"三年或10万公里"},{"specid":15932,"value":"三年或10万公里"},{"specid":15933,"value":"三年或10万公里"},{"specid":15931,"value":"三年或10万公里"},{"specid":15854,"value":"三年或10万公里"},{"specid":16167,"value":"三年或10万公里"}]}]},{"name":"车身","paramitems":[{"name":"长度(mm)","valueitems":[{"specid":15930,"value":"4860"},{"specid":15504,"value":"4860"},{"specid":15932,"value":"4860"},{"specid":15933,"value":"4860"},{"specid":15931,"value":"4860"},{"specid":15854,"value":"4860"},{"specid":16167,"value":"4860"}]},{"name":"宽度(mm)","valueitems":[{"specid":15930,"value":"1854"},{"specid":15504,"value":"1854"},{"specid":15932,"value":"1854"},{"specid":15933,"value":"1854"},{"specid":15931,"value":"1854"},{"specid":15854,"value":"1854"},{"specid":16167,"value":"1854"}]},{"name":"高度(mm)","valueitems":[{"specid":15930,"value":"1480"},{"specid":15504,"value":"1480"},{"specid":15932,"value":"1480"},{"specid":15933,"value":"1480"},{"specid":15931,"value":"1480"},{"specid":15854,"value":"1480"},{"specid":16167,"value":"1480"}]},{"name":"轴距(mm)","valueitems":[{"specid":15930,"value":"2850"},{"specid":15504,"value":"2850"},{"specid":15932,"value":"2850"},{"specid":15933,"value":"2850"},{"specid":15931,"value":"2850"},{"specid":15854,"value":"2850"},{"specid":16167,"value":"2850"}]},{"name":"前轮距(mm)","valueitems":[{"specid":15930,"value":"1578"},{"specid":15504,"value":"1578"},{"specid":15932,"value":"1578"},{"specid":15933,"value":"1578"},{"specid":15931,"value":"1578"},{"specid":15854,"value":"1578"},{"specid":16167,"value":"1578"}]},{"name":"后轮距(mm)","valueitems":[{"specid":15930,"value":"1574"},{"specid":15504,"value":"1574"},{"specid":15932,"value":"1574"},{"specid":15933,"value":"1574"},{"specid":15931,"value":"1574"},{"specid":15854,"value":"1574"},{"specid":16167,"value":"1574"}]},{"name":"最小离地间隙(mm)","valueitems":[{"specid":15930,"value":"124"},{"specid":15504,"value":"124"},{"specid":15932,"value":"124"},{"specid":15933,"value":"124"},{"specid":15931,"value":"124"},{"specid":15854,"value":"124"},{"specid":16167,"value":"124"}]},{"name":"整备质量(kg)","valueitems":[{"specid":15930,"value":"1540"},{"specid":15504,"value":"1540"},{"specid":15932,"value":"1659"},{"specid":15933,"value":"1659"},{"specid":15931,"value":"1659"},{"specid":15854,"value":"1659"},{"specid":16167,"value":"1659"}]},{"name":"车身结构","valueitems":[{"specid":15930,"value":"三厢车"},{"specid":15504,"value":"三厢车"},{"specid":15932,"value":"三厢车"},{"specid":15933,"value":"三厢车"},{"specid":15931,"value":"三厢车"},{"specid":15854,"value":"三厢车"},{"specid":16167,"value":"三厢车"}]},{"name":"车门数(个)","valueitems":[{"specid":15930,"value":"4"},{"specid":15504,"value":"4"},{"specid":15932,"value":"4"},{"specid":15933,"value":"4"},{"specid":15931,"value":"4"},{"specid":15854,"value":"4"},{"specid":16167,"value":"4"}]},{"name":"座位数(个)","valueitems":[{"specid":15930,"value":"5"},{"specid":15504,"value":"5"},{"specid":15932,"value":"5"},{"specid":15933,"value":"5"},{"specid":15931,"value":"5"},{"specid":15854,"value":"5"},{"specid":16167,"value":"5"}]},{"name":"油箱容积(L)","valueitems":[{"specid":15930,"value":"62"},{"specid":15504,"value":"62"},{"specid":15932,"value":"62"},{"specid":15933,"value":"62"},{"specid":15931,"value":"62"},{"specid":15854,"value":"62"},{"specid":16167,"value":"62"}]},{"name":"行李厢容积(L)","valueitems":[{"specid":15930,"value":"516-986"},{"specid":15504,"value":"516-986"},{"specid":15932,"value":"516-986"},{"specid":15933,"value":"516-986"},{"specid":15931,"value":"516-986"},{"specid":15854,"value":"516-986"},{"specid":16167,"value":"516-986"}]}]},{"name":"发动机","paramitems":[{"name":"发动机型号","valueitems":[{"specid":15930,"value":"-"},{"specid":15504,"value":"-"},{"specid":15932,"value":"-"},{"specid":15933,"value":"-"},{"specid":15931,"value":"-"},{"specid":15854,"value":"-"},{"specid":16167,"value":"-"}]},{"name":"排量(mL)","valueitems":[{"specid":15930,"value":"1499"},{"specid":15504,"value":"1499"},{"specid":15932,"value":"1999"},{"specid":15933,"value":"1999"},{"specid":15931,"value":"1999"},{"specid":15854,"value":"1999"},{"specid":16167,"value":"1999"}]},{"name":"排量(L)","valueitems":[{"specid":15930,"value":"1.5"},{"specid":15504,"value":"1.5"},{"specid":15932,"value":"2.0"},{"specid":15933,"value":"2.0"},{"specid":15931,"value":"2.0"},{"specid":15854,"value":"2.0"},{"specid":16167,"value":"2.0"}]},{"name":"进气形式","valueitems":[{"specid":15930,"value":"涡轮增压"},{"specid":15504,"value":"涡轮增压"},{"specid":15932,"value":"涡轮增压"},{"specid":15933,"value":"涡轮增压"},{"specid":15931,"value":"涡轮增压"},{"specid":15854,"value":"涡轮增压"},{"specid":16167,"value":"涡轮增压"}]},{"name":"气缸排列形式","valueitems":[{"specid":15930,"value":"L"},{"specid":15504,"value":"L"},{"specid":15932,"value":"L"},{"specid":15933,"value":"L"},{"specid":15931,"value":"L"},{"specid":15854,"value":"L"},{"specid":16167,"value":"L"}]},{"name":"气缸数(个)","valueitems":[{"specid":15930,"value":"4"},{"specid":15504,"value":"4"},{"specid":15932,"value":"4"},{"specid":15933,"value":"4"},{"specid":15931,"value":"4"},{"specid":15854,"value":"4"},{"specid":16167,"value":"4"}]},{"name":"每缸气门数(个)","valueitems":[{"specid":15930,"value":"4"},{"specid":15504,"value":"4"},{"specid":15932,"value":"4"},{"specid":15933,"value":"4"},{"specid":15931,"value":"4"},{"specid":15854,"value":"4"},{"specid":16167,"value":"4"}]},{"name":"压缩比","valueitems":[{"specid":15930,"value":"10"},{"specid":15504,"value":"10"},{"specid":15932,"value":"9.3"},{"specid":15933,"value":"9.3"},{"specid":15931,"value":"9.3"},{"specid":15854,"value":"9.3"},{"specid":16167,"value":"9.3"}]},{"name":"配气机构","valueitems":[{"specid":15930,"value":"DOHC"},{"specid":15504,"value":"DOHC"},{"specid":15932,"value":"DOHC"},{"specid":15933,"value":"DOHC"},{"specid":15931,"value":"DOHC"},{"specid":15854,"value":"DOHC"},{"specid":16167,"value":"DOHC"}]},{"name":"缸径(mm)","valueitems":[{"specid":15930,"value":"-"},{"specid":15504,"value":"-"},{"specid":15932,"value":"-"},{"specid":15933,"value":"-"},{"specid":15931,"value":"-"},{"specid":15854,"value":"-"},{"specid":16167,"value":"-"}]},{"name":"行程(mm)","valueitems":[{"specid":15930,"value":"-"},{"specid":15504,"value":"-"},{"specid":15932,"value":"-"},{"specid":15933,"value":"-"},{"specid":15931,"value":"-"},{"specid":15854,"value":"-"},{"specid":16167,"value":"-"}]},{"name":"最大马力(Ps)","valueitems":[{"specid":15930,"value":"181"},{"specid":15504,"value":"181"},{"specid":15932,"value":"203"},{"specid":15933,"value":"203"},{"specid":15931,"value":"242"},{"specid":15854,"value":"242"},{"specid":16167,"value":"242"}]},{"name":"最大功率(kW)","valueitems":[{"specid":15930,"value":"133"},{"specid":15504,"value":"133"},{"specid":15932,"value":"149"},{"specid":15933,"value":"149"},{"specid":15931,"value":"178"},{"specid":15854,"value":"178"},{"specid":16167,"value":"178"}]},{"name":"最大功率转速(rpm)","valueitems":[{"specid":15930,"value":"6500"},{"specid":15504,"value":"6500"},{"specid":15932,"value":"5500"},{"specid":15933,"value":"5500"},{"specid":15931,"value":"5500"},{"specid":15854,"value":"5500"},{"specid":16167,"value":"5500"}]},{"name":"最大扭矩(N・m)","valueitems":[{"specid":15930,"value":"240"},{"specid":15504,"value":"240"},{"specid":15932,"value":"340"},{"specid":15933,"value":"340"},{"specid":15931,"value":"350"},{"specid":15854,"value":"350"},{"specid":16167,"value":"350"}]},{"name":"最大扭矩转速(rpm)","valueitems":[{"specid":15930,"value":"1750-4500"},{"specid":15504,"value":"1750-4500"},{"specid":15932,"value":"3000"},{"specid":15933,"value":"3000"},{"specid":15931,"value":"3000"},{"specid":15854,"value":"3000"},{"specid":16167,"value":"3000"}]},{"name":"发动机特有技术","valueitems":[{"specid":15930,"value":"-"},{"specid":15504,"value":"-"},{"specid":15932,"value":"-"},{"specid":15933,"value":"-"},{"specid":15931,"value":"-"},{"specid":15854,"value":"-"},{"specid":16167,"value":"-"}]},{"name":"燃料形式","valueitems":[{"specid":15930,"value":"汽油"},{"specid":15504,"value":"汽油"},{"specid":15932,"value":"汽油"},{"specid":15933,"value":"汽油"},{"specid":15931,"value":"汽油"},{"specid":15854,"value":"汽油"},{"specid":16167,"value":"汽油"}]},{"name":"燃油标号","valueitems":[{"specid":15930,"value":"93号(京92号)"},{"specid":15504,"value":"93号(京92号)"},{"specid":15932,"value":"93号(京92号)"},{"specid":15933,"value":"93号(京92号)"},{"specid":15931,"value":"93号(京92号)"},{"specid":15854,"value":"93号(京92号)"},{"specid":16167,"value":"93号(京92号)"}]},{"name":"供油方式","valueitems":[{"specid":15930,"value":"直喷"},{"specid":15504,"value":"直喷"},{"specid":15932,"value":"直喷"},{"specid":15933,"value":"直喷"},{"specid":15931,"value":"直喷"},{"specid":15854,"value":"直喷"},{"specid":16167,"value":"直喷"}]},{"name":"缸盖材料","valueitems":[{"specid":15930,"value":"铝"},{"specid":15504,"value":"铝"},{"specid":15932,"value":"铝"},{"specid":15933,"value":"铝"},{"specid":15931,"value":"铝"},{"specid":15854,"value":"铝"},{"specid":16167,"value":"铝"}]},{"name":"缸体材料","valueitems":[{"specid":15930,"value":"铝"},{"specid":15504,"value":"铝"},{"specid":15932,"value":"铝"},{"specid":15933,"value":"铝"},{"specid":15931,"value":"铝"},{"specid":15854,"value":"铝"},{"specid":16167,"value":"铝"}]},{"name":"环保标准","valueitems":[{"specid":15930,"value":"国IV(京V)"},{"specid":15504,"value":"国IV(京V)"},{"specid":15932,"value":"国IV(京V)"},{"specid":15933,"value":"国IV(京V)"},{"specid":15931,"value":"国IV(京V)"},{"specid":15854,"value":"国IV(京V)"},{"specid":16167,"value":"国IV(京V)"}]}]},{"name":"变速箱","paramitems":[{"name":"简称","valueitems":[{"specid":15930,"value":"6挡手自一体"},{"specid":15504,"value":"6挡手自一体"},{"specid":15932,"value":"6挡手自一体"},{"specid":15933,"value":"6挡手自一体"},{"specid":15931,"value":"6挡手自一体"},{"specid":15854,"value":"6挡手自一体"},{"specid":16167,"value":"6挡手自一体"}]},{"name":"挡位个数","valueitems":[{"specid":15930,"value":"6"},{"specid":15504,"value":"6"},{"specid":15932,"value":"6"},{"specid":15933,"value":"6"},{"specid":15931,"value":"6"},{"specid":15854,"value":"6"},{"specid":16167,"value":"6"}]},{"name":"变速箱类型","valueitems":[{"specid":15930,"value":"自动变速箱(AT)"},{"specid":15504,"value":"自动变速箱(AT)"},{"specid":15932,"value":"自动变速箱(AT)"},{"specid":15933,"value":"自动变速箱(AT)"},{"specid":15931,"value":"自动变速箱(AT)"},{"specid":15854,"value":"自动变速箱(AT)"},{"specid":16167,"value":"自动变速箱(AT)"}]}]},{"name":"底盘转向","paramitems":[{"name":"驱动方式","valueitems":[{"specid":15930,"value":"前置前驱"},{"specid":15504,"value":"前置前驱"},{"specid":15932,"value":"前置前驱"},{"specid":15933,"value":"前置前驱"},{"specid":15931,"value":"前置前驱"},{"specid":15854,"value":"前置前驱"},{"specid":16167,"value":"前置前驱"}]},{"name":"前悬架类型","valueitems":[{"specid":15930,"value":"麦弗逊式独立悬架"},{"specid":15504,"value":"麦弗逊式独立悬架"},{"specid":15932,"value":"麦弗逊式独立悬架"},{"specid":15933,"value":"麦弗逊式独立悬架"},{"specid":15931,"value":"麦弗逊式独立悬架"},{"specid":15854,"value":"麦弗逊式独立悬架"},{"specid":16167,"value":"麦弗逊式独立悬架"}]},{"name":"后悬架类型","valueitems":[{"specid":15930,"value":"多连杆独立悬架"},{"specid":15504,"value":"多连杆独立悬架"},{"specid":15932,"value":"多连杆独立悬架"},{"specid":15933,"value":"多连杆独立悬架"},{"specid":15931,"value":"多连杆独立悬架"},{"specid":15854,"value":"多连杆独立悬架"},{"specid":16167,"value":"多连杆独立悬架"}]},{"name":"助力类型","valueitems":[{"specid":15930,"value":"电动助力"},{"specid":15504,"value":"电动助力"},{"specid":15932,"value":"电动助力"},{"specid":15933,"value":"电动助力"},{"specid":15931,"value":"电动助力"},{"specid":15854,"value":"电动助力"},{"specid":16167,"value":"电动助力"}]},{"name":"车体结构","valueitems":[{"specid":15930,"value":"承载式"},{"specid":15504,"value":"承载式"},{"specid":15932,"value":"承载式"},{"specid":15933,"value":"承载式"},{"specid":15931,"value":"承载式"},{"specid":15854,"value":"承载式"},{"specid":16167,"value":"承载式"}]}]},{"name":"车轮制动","paramitems":[{"name":"前制动器类型","valueitems":[{"specid":15930,"value":"通风盘式"},{"specid":15504,"value":"通风盘式"},{"specid":15932,"value":"通风盘式"},{"specid":15933,"value":"通风盘式"},{"specid":15931,"value":"通风盘式"},{"specid":15854,"value":"通风盘式"},{"specid":16167,"value":"通风盘式"}]},{"name":"后制动器类型","valueitems":[{"specid":15930,"value":"盘式"},{"specid":15504,"value":"盘式"},{"specid":15932,"value":"盘式"},{"specid":15933,"value":"盘式"},{"specid":15931,"value":"盘式"},{"specid":15854,"value":"盘式"},{"specid":16167,"value":"盘式"}]},{"name":"驻车制动类型","valueitems":[{"specid":15930,"value":"电子驻车"},{"specid":15504,"value":"电子驻车"},{"specid":15932,"value":"电子驻车"},{"specid":15933,"value":"电子驻车"},{"specid":15931,"value":"电子驻车"},{"specid":15854,"value":"电子驻车"},{"specid":16167,"value":"电子驻车"}]},{"name":"前轮胎规格","valueitems":[{"specid":15930,"value":"215/60 R16"},{"specid":15504,"value":"235/50 R17"},{"specid":15932,"value":"235/50 R17"},{"specid":15933,"value":"235/50 R17"},{"specid":15931,"value":"235/45 R18"},{"specid":15854,"value":"235/45 R18"},{"specid":16167,"value":"235/45 R18"}]},{"name":"后轮胎规格","valueitems":[{"specid":15930,"value":"215/60 R16"},{"specid":15504,"value":"235/50 R17 "},{"specid":15932,"value":"235/50 R17 "},{"specid":15933,"value":"235/50 R17 "},{"specid":15931,"value":"235/45 R18"},{"specid":15854,"value":"235/45 R18"},{"specid":16167,"value":"235/45 R18"}]},{"name":"备胎规格","valueitems":[{"specid":15930,"value":"非全尺寸"},{"specid":15504,"value":"非全尺寸"},{"specid":15932,"value":"非全尺寸"},{"specid":15933,"value":"非全尺寸"},{"specid":15931,"value":"非全尺寸"},{"specid":15854,"value":"非全尺寸"},{"specid":16167,"value":"非全尺寸"}]}]}]}}]        